nlp2cron.py
nlp2cron-0.1.4.dist-info/WHEEL
nlp2cron-0.1.4.dist-info/METADATA
nlp2cron-0.1.4.dist-info/RECORD
