Metadata-Version: 2.1
Name: nlp2cron
Version: 0.1.4
Summary: Nature language to cron
Author: quqinglei
Author-email: quqinglei@icloud.com
Requires-Python: >=3.9,<4.0
Classifier: Programming Language :: Python :: 3
Classifier: Programming Language :: Python :: 3.9
Classifier: Programming Language :: Python :: 3.10
Classifier: Programming Language :: Python :: 3.11
Requires-Dist: cn2an (>=0.5.19,<0.6.0)
